{
  "name": "Languages",
  "image": "/img/skills/languages.jpg",
  "entries": [
    {
      "name": "PHP",
      "date": "2018",
      "confidence": 50
    },
    {
      "name": [
        "JavaScript",
        "TypeScript"
      ],
      "date": "2018",
      "confidence": 50
    },
    {
      "name": "Java",
      "date": "2019",
      "confidence": 10
    },
    {
      "name": [
        "C++",
        "C# (.NET)",
        "C"
      ],
      "date": "2020-06-01",
      "confidence": 0
    },
    {
      "name": "Rust",
      "date": "2020-06-01",
      "confidence": 0
    }
  ]
}